cdxg/__init__.py
cdxg/appdriver.py
cdxg/case.py
cdxg/cli.py
cdxg/driver.py
cdxg/request.py
cdxg/skip.py
cdxg/webdriver.py
cdxg/webdriver_chaining.py
cdxg/appium_lab/__init__.py
cdxg/appium_lab/action.py
cdxg/appium_lab/find.py
cdxg/appium_lab/keyboard.py
cdxg/appium_lab/switch.py
cdxg/db_operation/__init__.py
cdxg/db_operation/base_db.py
cdxg/db_operation/mongo_db.py
cdxg/db_operation/mssql_db.py
cdxg/db_operation/mysql_db.py
cdxg/db_operation/sqlite_db.py
cdxg/har2case/__init__.py
cdxg/har2case/core.py
cdxg/har2case/utils.py
cdxg/logging/__init__.py
cdxg/logging/exceptions.py
cdxg/logging/log.py
cdxg/running/DebugTestRunner.py
cdxg/running/__init__.py
cdxg/running/config.py
cdxg/running/loader_extend.py
cdxg/running/loader_hook.py
cdxg/running/runner.py
cdxg/testdata/__init__.py
cdxg/testdata/conversion.py
cdxg/testdata/parameterization.py
cdxg/testdata/random_data.py
cdxg/testdata/random_func.py
cdxg/utils/__init__.py
cdxg/utils/cache.py
cdxg/utils/curlify.py
cdxg/utils/diff.py
cdxg/utils/file_extend.py
cdxg/utils/genson.py
cdxg/utils/jmespath.py
cdxg/utils/jsonpath.py
cdxg/utils/klook.py
cdxg/utils/send_extend.py
cdxg/utils/thread_lab.py
cdxg/utils/tomorrow.py
cdxg/utils/webdriver_manager_extend.py
cdxg-1.3.dist-info/LICENSE
cdxg-1.3.dist-info/METADATA
cdxg-1.3.dist-info/WHEEL
cdxg-1.3.dist-info/entry_points.txt
cdxg-1.3.dist-info/top_level.txt
cdxg-1.3.dist-info/RECORD
