Metadata-Version: 2.1
Name: cdxg
Version: 1.3
Summary: Cdxg automation testing framework.
Home-page: https://github.com/saasaa831/cdxg/
Author: mastersaa
Author-email: mastersaa@saa.com
License: Apache-2.0
Classifier: Intended Audience :: Developers
Classifier: Operating System :: MacOS :: MacOS X
Classifier: Operating System :: Microsoft :: Windows
Classifier: Programming Language :: Python
Classifier: Programming Language :: Python :: 3.7
Classifier: Programming Language :: Python :: 3.8
Classifier: Programming Language :: Python :: 3.9
Classifier: Programming Language :: Python :: 3.10
Classifier: Programming Language :: Python :: 3.11
Classifier: Topic :: Internet :: WWW/HTTP :: Dynamic Content
Classifier: Topic :: Software Development :: Testing
License-File: LICENSE
Requires-Dist: Appium-Python-Client (>=2.11.0)
Requires-Dist: parameterized (==0.8.1)
Requires-Dist: loguru (==0.6.0)
Requires-Dist: openpyxl (>=3.0.3)
Requires-Dist: pyyaml (>=6.0)
Requires-Dist: requests (>=2.22.0)
Requires-Dist: jsonschema (>=4.10.0)
Requires-Dist: jmespath (>=0.10.0)
Requires-Dist: webdriver-manager (~=4.0.0)
Requires-Dist: pymysql (>=1.0.0)
Requires-Dist: genson (==1.2.2)
Requires-Dist: click (~=8.1.3)
Requires-Dist: python-dateutil (==2.8.2)
